pyqupa/__init__.py
pyqupa/__main__.py
pyqupa/app.py
pyqupa/assets/__init__.py
pyqupa/assets/screenshots/__init__.py
pyqupa/assets/screenshots/search_by_distance.png
pyqupa/assets/screenshots/search_by_name.png
pyqupa/assets/screenshots/search_by_region.png
pyqupa/db/pass_names.json
pyqupa/db/passes.json
pyqupa/passes.py
pyqupa/quaeldich.py
pyqupa/tools.py
pyqupa-0.1.1.dist-info/WHEEL
pyqupa-0.1.1.dist-info/METADATA
pyqupa-0.1.1.dist-info/RECORD
