Metadata-Version: 2.1
Name: pyqupa
Version: 0.1.1
Summary: PYthon Qualdich.de mountain PAss data processor.
Author: Kyoungseoun Chung
Author-email: kyoungseoun.chung@gmail.com
Requires-Python: >=3.9,<3.10
Classifier: Programming Language :: Python :: 3
Classifier: Programming Language :: Python :: 3.9
Requires-Dist: bs4 (>=0.0.1,<0.0.2)
Requires-Dist: folium (>=0.12.1,<0.13.0)
Requires-Dist: lxml (>=4.9.1,<5.0.0)
Requires-Dist: numpy (>=1.23.2,<2.0.0)
Requires-Dist: plotly (>=5.10.0,<6.0.0)
Requires-Dist: pydeck (>=0.7.1,<0.8.0)
Requires-Dist: python-dotenv (>=0.20.0,<0.21.0)
Requires-Dist: rich (>=12.5.1,<13.0.0)
Requires-Dist: streamlit (>=1.12.2,<2.0.0)
Requires-Dist: streamlit-folium (>=0.6.15,<0.7.0)
Requires-Dist: tinydb (>=4.7.0,<5.0.0)
